widgeon/__init__.py
widgeon/pg.py
widgeon/data/empty_icon.png
widgeon/data/icon.png
widgeon-0.0.2.dist-info/LICENSE
widgeon-0.0.2.dist-info/METADATA
widgeon-0.0.2.dist-info/WHEEL
widgeon-0.0.2.dist-info/top_level.txt
widgeon-0.0.2.dist-info/RECORD
