Metadata-Version: 2.1
Name: widgeon
Version: 0.0.2
Summary: A simple tool for building UIs
Home-page: https://github.com/dots-git/widgets
Author: Simon Kriele
Author-email: kriele.simon@gmail.com
License: UNKNOWN
Project-URL: Bug Tracker, https://github.com/dots-git/widgets/issues
Platform: UNKNOWN
Classifier: Programming Language :: Python :: 3
Classifier: License :: OSI Approved :: GNU General Public License v3 (GPLv3)
Classifier: Operating System :: OS Independent
Requires-Python: >=3.6
License-File: LICENSE
